defistream/__init__.py
defistream/client.py
defistream/exceptions.py
defistream/models.py
defistream/protocols.py
defistream/py.typed
defistream/query.py
defistream-1.2.1.dist-info/METADATA
defistream-1.2.1.dist-info/WHEEL
defistream-1.2.1.dist-info/licenses/LICENSE
defistream-1.2.1.dist-info/RECORD
