Metadata-Version: 2.4
Name: defistream
Version: 1.2.1
Summary: Python client for the DeFiStream API
Project-URL: Homepage, https://defistream.dev
Project-URL: Documentation, https://docs.defistream.dev
Project-URL: Repository, https://github.com/Eren-Nevin/DeFiStream_PythonClient
Author-email: DeFiStream <support@defistream.dev>
License-Expression: MIT
License-File: LICENSE
Keywords: api,blockchain,crypto,defi,ethereum,web3
Classifier: Development Status :: 4 - Beta
Classifier: Intended Audience :: Developers
Classifier: License :: OSI Approved :: MIT License
Classifier: Programming Language :: Python :: 3
Classifier: Programming Language :: Python :: 3.9
Classifier: Programming Language :: Python :: 3.10
Classifier: Programming Language :: Python :: 3.11
Classifier: Programming Language :: Python :: 3.12
Classifier: Topic :: Software Development :: Libraries :: Python Modules
Classifier: Typing :: Typed
Requires-Python: >=3.9
Requires-Dist: httpx>=0.25.0
Requires-Dist: pandas>=2.0.0
Requires-Dist: pyarrow>=14.0.0
Requires-Dist: pydantic>=2.0.0
Provides-Extra: dev
Requires-Dist: pytest-asyncio>=0.21.0; extra == 'dev'
Requires-Dist: pytest>=7.0.0; extra == 'dev'
Requires-Dist: python-dotenv>=1.0.0; extra == 'dev'
Provides-Extra: polars
Requires-Dist: polars>=0.20.0; extra == 'polars'
